wechatarticles/AccountBiz.py
wechatarticles/AlbumInfo.py
wechatarticles/ArticlesAPI.py
wechatarticles/ArticlesInfo.py
wechatarticles/ArticlesUrls.py
wechatarticles/DataType.py
wechatarticles/GetUrls.py
wechatarticles/ReadOutfile.py
wechatarticles/Url2Html.py
wechatarticles/WechatBook.py
wechatarticles/__init__.py
wechatarticles/nickname2biz.py
wechatarticles/proxy.py
wechatarticles/tools.py
wechatarticles/utils.py
wechatarticles-0.7.0.dist-info/LICENSE
wechatarticles-0.7.0.dist-info/METADATA
wechatarticles-0.7.0.dist-info/WHEEL
wechatarticles-0.7.0.dist-info/top_level.txt
wechatarticles-0.7.0.dist-info/RECORD
