Metadata-Version: 2.1
Name: wechatarticles
Version: 0.7.0
Summary: wechat articles scrapy
Home-page: https://github.com/wnma3mz/wechat_articles_spider
Author: wnma3mz
Author-email: wnma3mz@gmail.com
License: UNKNOWN
Platform: UNKNOWN
Classifier: Programming Language :: Python :: 3
Classifier: License :: OSI Approved :: Apache Software License
Classifier: Operating System :: OS Independent
Requires-Dist: requests (>=2.20.0)
Requires-Dist: beautifulsoup4 (>=4.7.1)
